skymapper/__init__.py
skymapper/config.py
skymapper/core.py
skymapping_tools-0.8.8.dist-info/LICENSE
skymapping_tools-0.8.8.dist-info/METADATA
skymapping_tools-0.8.8.dist-info/WHEEL
skymapping_tools-0.8.8.dist-info/top_level.txt
skymapping_tools-0.8.8.dist-info/RECORD
