Metadata-Version: 2.1
Name: skymapping-tools
Version: 0.8.8
Summary: A tool for sequence data classification
Home-page: https://https://github.com/zwang2019/Garvan
Author: Zhao WANG, Tansel Ersavas
Author-email: zhao.wang.unsw@gmail.com, t.ersavas@garvan.org.au
License: Apache 2.0
Keywords: skymapper machine learning
Platform: UNKNOWN
Classifier: Development Status :: 3 - Alpha
Classifier: Intended Audience :: Developers
Classifier: Intended Audience :: Education
Classifier: Intended Audience :: Science/Research
Classifier: Topic :: Scientific/Engineering
Classifier: Topic :: Scientific/Engineering :: Artificial Intelligence
Classifier: Topic :: Software Development
Classifier: Topic :: Software Development :: Libraries
Classifier: License :: OSI Approved :: Apache Software License
Classifier: Programming Language :: Python :: 3
Classifier: Programming Language :: Python :: 3.6
Classifier: Programming Language :: Python :: 3.7
Requires-Python: >=3.6
Requires-Dist: tensorflow (==2.1.0)
Requires-Dist: scanpy
Requires-Dist: pycm (==2.5)
